pywaterkotte/__about__.py
pywaterkotte/__init__.py
pywaterkotte/ecotouch.py
pywaterkotte/sample.py
pywaterkotte-0.1.2.dist-info/METADATA
pywaterkotte-0.1.2.dist-info/WHEEL
pywaterkotte-0.1.2.dist-info/licenses/LICENSE
pywaterkotte-0.1.2.dist-info/RECORD
