Metadata-Version: 2.1
Name: pywaterkotte
Version: 0.1.2
Summary: pywaterkotte is a library to communicate with Waterkotte heatpumps.
Project-URL: Documentation, https://github.com/chboland/pywaterkotte#readme
Project-URL: Issues, https://github.com/chboland/pywaterkotte/issues
Project-URL: Source, https://github.com/chboland/pywaterkotte
Author-email: Christian Boland <github@chbol.de>
License-Expression: MIT
License-File: LICENSE
Classifier: Development Status :: 4 - Beta
Classifier: Programming Language :: Python
Classifier: Programming Language :: Python :: 3.7
Classifier: Programming Language :: Python :: 3.8
Classifier: Programming Language :: Python :: 3.9
Classifier: Programming Language :: Python :: 3.10
Classifier: Programming Language :: Python :: 3.11
Classifier: Programming Language :: Python :: Implementation :: CPython
Classifier: Programming Language :: Python :: Implementation :: PyPy
Requires-Python: >=3.7
Requires-Dist: requests
